MANIFEST.in
README.md
modulated_deform_conv.py
setup.cfg
setup.py
modulated_deform_conv.egg-info/PKG-INFO
modulated_deform_conv.egg-info/SOURCES.txt
modulated_deform_conv.egg-info/dependency_links.txt
modulated_deform_conv.egg-info/not-zip-safe
modulated_deform_conv.egg-info/top_level.txt
src/config.h
src/deformable_conv.cu
src/deformable_conv3d.cu
src/mdeformable_conv.cu
src/mdeformable_conv3d.cu
src/utils.cu
src/warp.cpp