Metadata-Version: 2.1
Name: modulated-deform-conv
Version: 1.0.1
Summary: cuda implementation of deformable conv2d, modulated deformable conv2d,deformable conv3d, modulated deformable conv3d
Home-page: https://www.github.com
Author: qiaoxin
Author-email: qiaoxin182@gmail.com
License: UNKNOWN
Platform: UNKNOWN
Classifier: Development Status :: 3 - Alpha
Classifier: Operating System :: POSIX :: Linux
Classifier: Intended Audience :: Developers
Classifier: License :: OSI Approved :: MIT License
Classifier: Programming Language :: Python :: 3
Classifier: Programming Language :: Python :: 3.3
Classifier: Programming Language :: Python :: 3.4
Classifier: Programming Language :: Python :: 3.5
Classifier: Programming Language :: Python :: 3.6
Classifier: Programming Language :: Python :: 3.7
